drf_embedded_fields/__init__.py
drf_embedded_fields/api_fields.py
drf_embedded_fields/base.py
drf_embedded_fields/exceptions.py
drf_embedded_fields/model_fields.py
drf_embedded_fields-0.1.dist-info/LICENSE
drf_embedded_fields-0.1.dist-info/METADATA
drf_embedded_fields-0.1.dist-info/WHEEL
drf_embedded_fields-0.1.dist-info/top_level.txt
drf_embedded_fields-0.1.dist-info/RECORD
