Metadata-Version: 2.1
Name: drf-embedded-fields
Version: 0.1
Summary: Provides Fields/Serializers that can be embedded through querystring
Home-page: https://github.com/Mendes11/drf_embedded_fields
Author: Rafael Mendes Pacini Bachiega
Author-email: rafaelmpb11@hotmail.com
License: UNKNOWN
Platform: UNKNOWN
Classifier: Intended Audience :: Developers
Classifier: Operating System :: OS Independent
Classifier: Programming Language :: Python :: 3 :: Only
Classifier: Programming Language :: Python :: 3.6
Classifier: Programming Language :: Python :: 3.7
Classifier: Programming Language :: Python :: 3.8
Requires-Dist: Django (>=2.2)
Requires-Dist: djangorestframework (>=3.1)
